ciel/__init__.py
ciel/__main__.py
ciel/__version__.py
ciel/build/__init__.py
ciel/build/common.py
ciel/build/gf180mcu.py
ciel/build/git_multi_clone.py
ciel/build/ihp-sg13g2.py
ciel/build/sky130.py
ciel/click_common.py
ciel/common.py
ciel/families.py
ciel/github.py
ciel/manage.py
ciel/py.typed
ciel/source.py
ciel-2.3.0.dist-info/METADATA
ciel-2.3.0.dist-info/WHEEL
ciel-2.3.0.dist-info/entry_points.txt
ciel-2.3.0.dist-info/RECORD
