Metadata-Version: 2.1
Name: ciel
Version: 2.3.0
Summary: An PDK builder/version manager for PDKs in the open_pdks format
Home-page: https://github.com/fossi-foundation/ciel
License: Apache-2.0
Author: Mohamed Gaber
Author-email: me@donn.website
Requires-Python: >=3.8
Classifier: Intended Audience :: Developers
Classifier: License :: OSI Approved :: Apache Software License
Classifier: Operating System :: MacOS :: MacOS X
Classifier: Operating System :: POSIX :: Linux
Classifier: Programming Language :: Python :: 3
Classifier: Programming Language :: Python :: 3.8
Classifier: Programming Language :: Python :: 3.9
Classifier: Programming Language :: Python :: 3.10
Classifier: Programming Language :: Python :: 3.11
Classifier: Programming Language :: Python :: 3.12
Classifier: Programming Language :: Python :: 3.13
Requires-Dist: click (>=8,<9)
Requires-Dist: httpx (>=0.22.0,<0.29)
Requires-Dist: pcpp (>=1.2,<2)
Requires-Dist: pyyaml (>=5,<7)
Requires-Dist: rich (>=12,<15)
Requires-Dist: zstandard (>=0.19.0,<1)
Project-URL: Repository, https://github.com/fossi-foundation/ciel
